tg_bot/__init__.py
tg_bot/sdk.py
tgbot_py-0.3.dist-info/LICENSE
tgbot_py-0.3.dist-info/METADATA
tgbot_py-0.3.dist-info/WHEEL
tgbot_py-0.3.dist-info/top_level.txt
tgbot_py-0.3.dist-info/RECORD
